Metadata-Version: 2.1
Name: tapi-yandex-market
Version: 1.0.0
Summary: Python client for API Yandex Market
Home-page: https://github.com/pavelmaksimov/tapi-yandex-market
Author: Pavel Maksimov
Author-email: vur21@ya.ru
License: MIT
Keywords: tapi,yandex,market,api,client,яндекс,маркет,апи
Platform: UNKNOWN
License-File: LICENSE
